bridge/__init__.py
bridge/config.py
bridge/console.py
bridge/cli/__init__.py
bridge/cli/bridge.py
bridge/cli/errors.py
bridge/cli/stop.py
bridge/cli/db/__init__.py
bridge/cli/init/__init__.py
bridge/cli/init/install_deps.py
bridge/cli/init/render.py
bridge/cli/init/templates/__init__.py
bridge/cli/init/templates/build__sh.py
bridge/cli/init/templates/build_worker__sh.py
bridge/cli/init/templates/deploy_to_render_button.py
bridge/cli/init/templates/render__yaml.py
bridge/cli/init/templates/start__sh.py
bridge/cli/init/templates/start_worker__sh.py
bridge/cli/redis/__init__.py
bridge/framework/__init__.py
bridge/framework/base.py
bridge/framework/django.py
bridge/platform/__init__.py
bridge/platform/base.py
bridge/platform/postgres.py
bridge/platform/redis.py
bridge/platform/render/__init__.py
bridge/platform/render/postgres.py
bridge/platform/render/redis.py
bridge/service/__init__.py
bridge/service/django_celery.py
bridge/service/docker.py
bridge/service/postgres.py
bridge/service/redis.py
bridge/utils/__init__.py
bridge/utils/filesystem.py
bridge/utils/pydantic.py
bridge/utils/sanitize.py
python_bridge-0.1.2.dist-info/LICENSE
python_bridge-0.1.2.dist-info/METADATA
python_bridge-0.1.2.dist-info/WHEEL
python_bridge-0.1.2.dist-info/entry_points.txt
python_bridge-0.1.2.dist-info/top_level.txt
python_bridge-0.1.2.dist-info/RECORD
